{
  "resourceType": "StructureDefinition",
  "id": "8e41ae3e-5362-4413-bfa3-750418853039",
  "meta": {
    "lastUpdated": "2021-04-28T17:32:07.373+00:00"
  },
  "url": "https://apifhir.annuaire.sante.fr/ws-sync/exposed/structuredefinition/practitionerRole-vitaleAccepted",
  "version": "1.0",
  "name": "PractitionerRoleVitaleAccepted",
  "status": "active",
  "date": "2021-03-25T17:50:38.748626+00:00",
  "publisher": "ANS",
  "contact": [
    {
      "name": "monserviceclient.annuaire@asipsante.fr"
    }
  ],
  "fhirVersion": "4.0.1",
  "mapping": [
    {
      "identity": "rim",
      "uri": "http://hl7.org/v3",
      "name": "RIM Mapping"
    }
  ],
  "kind": "complex-type",
  "abstract": false,
  "context": [
    {
      "type": "element",
      "expression": "PractitionerRole"
    }
  ],
  "type": "Extension",
  "baseDefinition": "http://hl7.org/fhir/StructureDefinition/Extension",
  "derivation": "constraint",
  "differential": {
    "element": [
      {
        "id": "Extension.url",
        "path": "Extension.url",
        "fixedUri": "https://apifhir.annuaire.sante.fr/ws-sync/exposed/structuredefinition/practitionerRole-vitaleAccepted"
      },
      {
        "id": "Extension.value[x]",
        "path": "Extension.value[x]",
        "type": [
          {
            "code": "boolean"
          }
        ]
      }
    ]
  }
}